{
  "project_info": {
    "project_number": "1025611620113",
    "project_id": "fir-basic-all",
    "storage_bucket": "fir-basic-all.appspot.com"
  },
  "client": [
    {
      "client_info": {
        "mobilesdk_app_id": "1:1025611620113:android:7544cff47b035c999a76b0",
        "android_client_info": {
          "package_name": "com.example.firebase"
        }
      },
      "oauth_client": [
        {
          "client_id": "1025611620113-1nai7a547eai4mb2u0i2vqlbehk2iarb.apps.googleusercontent.com",
          "client_type": 3
        }
      ],
      "api_key": [
        {
          "current_key": "AIzaSyDbJTuld_t8Js8RQupCmhSS3Oskt8-VEb4"
        }
      ],
      "services": {
        "appinvite_service": {
          "other_platform_oauth_client": [
            {
              "client_id": "1025611620113-1nai7a547eai4mb2u0i2vqlbehk2iarb.apps.googleusercontent.com",
              "client_type": 3
            }
          ]
        }
      }
    }
  ],
  "configuration_version": "1"
}